ast_predicates/__init__.py
ast_predicates/core.py
ast_predicates/matchers.py
ast_predicates/nodes.py
ast_predicates/py.typed
ast_predicates/types.py
ast_predicates-1.0.2.dist-info/WHEEL
ast_predicates-1.0.2.dist-info/METADATA
ast_predicates-1.0.2.dist-info/RECORD
