Metadata-Version: 2.4
Name: ast-predicates
Version: 1.0.2
Summary: A Python library for matching and querying Python AST nodes
Author: Xavier Barbosa
Author-email: Xavier Barbosa <clint.northwood@gmail.com>
License-Expression: MIT
Classifier: Development Status :: 5 - Production/Stable
Classifier: Intended Audience :: Developers
Classifier: Topic :: Software Development :: Libraries
Classifier: Programming Language :: Python
Classifier: Programming Language :: Python :: 3
Classifier: Programming Language :: Python :: 3 :: Only
Classifier: Programming Language :: Python :: 3.12
Classifier: Programming Language :: Python :: 3.13
Classifier: Programming Language :: Python :: 3.14
Requires-Python: >=3.12
Project-URL: Homepage, https://github.com/johnnoone/python-ast-predicates
Project-URL: Source, https://github.com/johnnoone/python-ast-predicates
Project-URL: Tracker, https://github.com/johnnoone/python-ast-predicates/issues
